setup.cfg
setup.py
wellrng/__init__.py
wellrng/well1024a.py
wellrng.egg-info/PKG-INFO
wellrng.egg-info/SOURCES.txt
wellrng.egg-info/dependency_links.txt
wellrng.egg-info/top_level.txt