Metadata-Version: 1.1
Name: wellrng
Version: 0.1
Summary: A replacment for the default random lib using WELL1024a RNG
Home-page: https://github.com/rphlo/py-wellrng
Author: Raphael Stefanini
Author-email: stef.raphael@gmail.com
License: UNKNOWN
Download-URL: https://github.com/rphlo/py-wellrng/tarball/0.1
Keywords: random,well1024a,PRNG,RNG
Platform: UNKNOWN
